austriadownloader/__init__.py
austriadownloader/austria_data/__init__.py
austriadownloader/austria_data/downloaded_data/Aktualität Orthophoto Operate Farbe und Infrarot.cpg
austriadownloader/austria_data/downloaded_data/Aktualität Orthophoto Operate Farbe und Infrarot.dbf
austriadownloader/austria_data/downloaded_data/Aktualität Orthophoto Operate Farbe und Infrarot.prj
austriadownloader/austria_data/downloaded_data/Aktualität Orthophoto Operate Farbe und Infrarot.sbn
austriadownloader/austria_data/downloaded_data/Aktualität Orthophoto Operate Farbe und Infrarot.sbx
austriadownloader/austria_data/downloaded_data/Aktualität Orthophoto Operate Farbe und Infrarot.shp
austriadownloader/austria_data/downloaded_data/Aktualität Orthophoto Operate Farbe und Infrarot.shp.xml
austriadownloader/austria_data/downloaded_data/Aktualität Orthophoto Operate Farbe und Infrarot.shx
austriadownloader/austria_data/matched_metadata.gpkg
austriadownloader/austria_data/metadata_creation.py
austriadownloader/configmanager.py
austriadownloader/data.py
austriadownloader/download.py
austriadownloader/downloadmanager.py
austriadownloader/downloadstate.py
austriadownloader-0.0.41.dist-info/LICENSE
austriadownloader-0.0.41.dist-info/METADATA
austriadownloader-0.0.41.dist-info/WHEEL
austriadownloader-0.0.41.dist-info/RECORD
