Metadata-Version: 2.1
Name: austriadownloader
Version: 0.0.41
Summary: Austriadownloader is a Python package for downloading Austrian Cadastral and corresponding Orthophoto data for Deep Learning applications.
Home-page: https://github.com/Zerhigh/austriadownloader
Author: Samuel
Author-email: samuel@plix.at
Requires-Python: >=3.10,<4.0
Classifier: Programming Language :: Python :: 3
Classifier: Programming Language :: Python :: 3.10
Classifier: Programming Language :: Python :: 3.11
Requires-Dist: PyYAML (>=6.0.2)
Requires-Dist: fiona (>=1.10.1)
Requires-Dist: geopandas (>=1.0.1)
Requires-Dist: numpy (>=2.2.3)
Requires-Dist: pandas (>=2.2.3)
Requires-Dist: pillow (>=11.2.1)
Requires-Dist: pydantic (>=2.11.7)
Requires-Dist: pyproj (>=3.7.1)
Requires-Dist: pytest (>=8.4.0)
Requires-Dist: rasterio (>=1.4.3)
Requires-Dist: shapely (>=2.0.7)
Requires-Dist: tqdm (>=4.67.1)
Project-URL: Documentation, https://Zerhigh.github.io/austriadownloader/
Project-URL: Repository, https://github.com/Zerhigh/austriadownloader
